{"SL00001":{"SalesNo":"SL00001","Customer":"a1","Date":"2016-03-08T07:18:22.047Z","Items":[{"Id":"001","MPR":25,"Quantity":10,"Price":25}],"Discount":"","TotalAmount":250,"PaymentMethod":"Cash","PaymentAmount":250},"SL00002":{"SalesNo":"SL00002","Customer":"c1","Date":"2016-03-08T07:18:34.220Z","Items":[{"Id":"001","MPR":25,"Quantity":2,"Price":25}],"Discount":"","TotalAmount":50,"PaymentMethod":"Cash","PaymentAmount":50},"SL00003":{"SalesNo":"SL00003","Customer":"c1","Date":"2016-03-09T18:48:26.629Z","Items":[{"Id":"001","MPR":25,"Quantity":1,"Price":25}],"Discount":"","TotalAmount":25,"PaymentMethod":"Cash","PaymentAmount":25},"SL00004":{"SalesNo":"SL00004","Customer":"c1","Date":"2016-03-09T18:49:45.106Z","Items":[{"Id":"001","MPR":25,"Quantity":1,"Price":25}],"Discount":"","TotalAmount":25,"PaymentMethod":"Cash","PaymentAmount":""},"SL00005":{"SalesNo":"SL00005","Customer":"c1","Date":"2016-03-09T19:30:40.046Z","Items":[{"Id":"001","MPR":25,"Quantity":2,"Price":25}],"Discount":"","TotalAmount":50,"PaymentMethod":"Cash","PaymentAmount":""},"SL00006":{"SalesNo":"SL00008","Customer":"c1","Date":"2016-03-09T19:40:32.664Z","Items":[{"Id":"001","MPR":25,"Quantity":1,"Price":25}],"Discount":"","TotalAmount":25,"PaymentMethod":"Cash","PaymentAmount":""},"SL00007":{"SalesNo":"SL00008","Customer":"c1","Date":"2016-03-09T19:40:32.664Z","Items":[{"Id":"001","MPR":25,"Quantity":1,"Price":25}],"Discount":"","TotalAmount":25,"PaymentMethod":"Cash","PaymentAmount":""},"SL00008":{"SalesNo":"SL00008","Customer":"c1","Date":"2016-03-09T19:40:32.664Z","Items":[{"Id":"001","MPR":25,"Quantity":1,"Price":25}],"Discount":"","TotalAmount":25,"PaymentMethod":"Cash","PaymentAmount":""},"SL00009":{"SalesNo":"SL00009","Customer":"c1","Date":"2016-03-09T19:40:51.293Z","Items":[{"Id":"001","MPR":25,"Quantity":1,"Price":25}],"Discount":"","TotalAmount":25,"PaymentMethod":"Cash","PaymentAmount":""},"SL00010":{"SalesNo":"SL00010","Customer":"c1","Date":"2016-03-09T19:46:18.404Z","Items":[{"Id":"001","MPR":25,"Quantity":2,"Price":25}],"Discount":"","TotalAmount":50,"PaymentMethod":"Cash","PaymentAmount":23}}